pyfortimanager/__init__.py
pyfortimanager/core/__init__.py
pyfortimanager/core/api.py
pyfortimanager/core/fortimanager.py
pyfortimanager/models/__init__.py
pyfortimanager/models/adoms.py
pyfortimanager/models/cli_template_groups.py
pyfortimanager/models/device_groups.py
pyfortimanager/models/fortiaps.py
pyfortimanager/models/fortiaps_proxy.py
pyfortimanager/models/fortigates.py
pyfortimanager/models/fortigates_proxy.py
pyfortimanager/models/fortiswitches.py
pyfortimanager/models/fortiswitches_proxy.py
pyfortimanager/models/install_wizard.py
pyfortimanager/models/metadata_variables.py
pyfortimanager/models/policy_packages.py
pyfortimanager/models/radius_servers.py
pyfortimanager/models/scripts.py
pyfortimanager/models/sdwan_templates.py
pyfortimanager/models/system.py
pyfortimanager-2.3.2.dist-info/LICENSE
pyfortimanager-2.3.2.dist-info/METADATA
pyfortimanager-2.3.2.dist-info/WHEEL
pyfortimanager-2.3.2.dist-info/top_level.txt
pyfortimanager-2.3.2.dist-info/RECORD
