Metadata-Version: 2.1
Name: pyfortimanager
Version: 2.3.2
Summary: Python API client library for Fortinet's FortiManager.
Home-page: https://github.com/BESTSELLER/pyfortimanager
Author: Rasmus Thing
Author-email: network@bestseller.com
License: Apache2
Keywords: fortinet,fortimanager
Classifier: Intended Audience :: Developers
Classifier: Programming Language :: Python :: 3.8
Classifier: Programming Language :: Python :: 3.9
Classifier: Programming Language :: Python :: 3.10
Classifier: Programming Language :: Python :: 3.11
Classifier: Programming Language :: Python :: 3.12
Requires-Python: >=3.8, <4
License-File: LICENSE
Requires-Dist: requests<3.0,>=2.20.0
